{
    "香りの言葉": ["oci値について", "蒸気圧について", "香調（ノート）について", "揮発度指数について", "官能基について", "脂肪族化合物について", "脂環式化合物について", "芳香族化合物について", "テルペン化合物について", "ヘテロ環化合物について"],
    "香りのノート": ["シトラス", "アルデハイディック", "グリーン", "フルーティ", "ハーバル", "アロマティック", "スパイシー", "フローラル", "ウッディ", "アーシィ", "モッシィ", "バルサミック", "ハニー", "レザー", "アニマリック", "オリエンタル", "アンバー", "ムスキー", "パウダリー", "ニューフレッシュ", "マリン", "フゼア", "シプレ", "グルマン"],
    "匂いの種類": ["カビ臭", "塩素臭", "腐敗臭", "溶剤臭", "薬品臭"],
    "香りの成分": ["メチルヘプテノン", "オクタナール", "シス-3-ヘキセノール", "マツタケオール", "酢酸シス-3-ヘキセニル", "シス-ジャスモン", "ジャスモン酸メチル", "アネトール", "エストラゴール", "ラズベリーケトン", "ベンズアルデヒド", "シンナミックアルデヒド", "クミンアルデヒ", "ベンジルアルコール", "酢酸ベンジル", "フェニルエチルアルコール", "シンナミックアルコール", "安息香酸", "安息香酸メチル", "サリチル酸メチル", "安息香酸ベンジル", "アンスラニル酸メチル", "チモール", "オイゲノール", "メチルオイゲノール", "バニリン", "ミルセン", "サビネン", "カンフェン", "α-ピネン", "β-ピネン", "リモネン", "γ-ターピネン", "p-サイメン", "カマズレン", "β-カリオフィレン", "ファルネセン", "ゲルマクレンD", "カリオフィレンオキサイド", "1,8-シネオール", "カルボン", "ツヨン", "カンファー", "ベルベノン", "ヌートカトン", "α-ヨノン", "α-ダマスコン", "シトロネラール", "シトラール", "シトロネロール", "酢酸シトロネリル", "ネロール", "酢酸ネリル", "ゲラニオール", "酢酸ゲラニル", "ファルネソール", "メントール", "ボルネオール", "リナロール", "酢酸リナリル", "α-ターピネオール", "酢酸タービニル", "ターピネン-4-オール", "ネロリドール", "α-ビサポロール", "セドロール", "シス-α-サンタロール", "パチュリアルコール", "γデカラクトン", "ジャスミンラクトン", "クマリン", "インドール"],
    "精油": ["アカエゾマツ", "アニス", "イランイラン", "イリス", "ウコン", "ウメ", "オレンジ", "カーネーション (アブソリュート)", "カフィアライム", "カモミール・ジャーマン", "カモミール・ローマン", "カルダモン", "ガルバナム", "キャロットシード", "キンモクセイ", "クスノキ", "クチナシ/ガーデニア", "クミン", "クラリセージ", "グレープフルーツ", "クローブ", "クロモジ", "ゲットウ", "コウヤマキ", "コリアンダー", "サイプレス", "サクラ", "サンダルウッド", "シークワーサー", "システ", "シソ", "シダーウッド", "シダーウッド・バージニア", "シトロネラ", "シナモン", "シベリアモミ", "ジャーマンカモミール", "ジャスミン", "ジャスミンサンバック (アブソリュート)", "ジュニパーベリー", "ジョンキル", "ジンジャー", "ジンチョウゲ", "スイートオレンジ", "スイートマージョラム", "スギ", "スギ 〈枝葉)", "スギ 〈木部〉", "スパイクラベンダー", "スペアミント", "セージ", "ゼラニウム", "タイム", "ダパナ", "チュベローズ", "ティートリー", "トドマツ", "トンカビーンズ(アブソリュート)", "ナツメグ", "ニアウリ", "ニオイコブシ", "ネロリ", "バイオレットリーフ (アブソリュート)", "パイン", "バジル", "パチュリ", "ハッカ", "ハニーサックル", "バニラ (アブソリュート)", "ハマナス", "パルマローザ", "ヒノキ", "ヒバ", "フェンネル", "プチグレン", "ブラックスプルース", "ブラックペッパー", "フランキンセンス", "プルメリア", "ベチバー", "ペパーミント", "ベルガモット", "ベンゾイン (レジノイド)", "ベンゾイン(安息香)", "ホーリーフ/芳樟", "ボローニア", "マジョラム", "マヌカ", "マンダリン", "ミカン", "ミケリアアルバ", "ミケリアチャンパカ", "ミモザ(アブソリュート)", "ミルラ", "メイチャン", "メリッサ", "モミノトドマツ", "ヤロウ", "ユーカリ", "ユズ", "ライム", "ライラック", "ラバンディン", "ラブラドールティー", "ラベンダー", "リセアクベバ", "レモン", "レモングラス", "レモンユーカリ", "ローズ(アブソリュート)", "ローズ・センティフォーリア", "ローズ・ダマセナ", "ローズウッド", "ローズオットー", "ローズマリー", "ローマンカモミール", "ローレル", "青森ヒバ", "八朔", "芳樟",       "没薬"]
}